drivelinepy/__init__.py
drivelinepy/acuity_api.py
drivelinepy/base_api_wrapper.py
drivelinepy/brightpearl_api.py
drivelinepy/flex_pro_grip_api.py
drivelinepy/slack_api.py
drivelinepy/traq_api.py
drivelinepy/virtuagym_api.py
drivelinepy/zoho_billing_api.py
drivelinepy/zoho_crm_api.py
drivelinepy/zoho_sign_api.py
drivelinepy-1.19.0.dist-info/LICENSE
drivelinepy-1.19.0.dist-info/METADATA
drivelinepy-1.19.0.dist-info/WHEEL
drivelinepy-1.19.0.dist-info/top_level.txt
drivelinepy-1.19.0.dist-info/RECORD
