Metadata-Version: 2.1
Name: drivelinepy
Version: 1.19.0
Summary: A Python package for Driveline Baseball API interactions
Home-page: https://github.com/drivelineresearch/drivelinepy
Author: Garrett York
Author-email: garrett@drivelinebaseball.com
Classifier: Programming Language :: Python :: 3.8
Classifier: Programming Language :: Python :: 3.9
Classifier: Programming Language :: Python :: 3.10
Classifier: Programming Language :: Python :: 3.11
Classifier: License :: OSI Approved :: MIT License
Classifier: Operating System :: OS Independent
Requires-Python: >=3.8
License-File: LICENSE
Requires-Dist: python-dotenv <2.0.0,>=1.0.1
Requires-Dist: requests <3.0.0,>=2.31.0
Requires-Dist: urllib3 <3.0.0,>=2.2.0
